CHANGELOG.md
README.md
examples/README.md
pytermgui/__init__.py
pytermgui/animations.py
pytermgui/ansi_interface.py
pytermgui/cell.py
pytermgui/cmd.py
pytermgui/color_info.py
pytermgui/colors.py
pytermgui/context_managers.py
pytermgui/enums.py
pytermgui/exceptions.py
pytermgui/exporters.py
pytermgui/fancy_repr.py
pytermgui/file_loaders.py
pytermgui/helpers.py
pytermgui/highlighters.py
pytermgui/input.py
pytermgui/inspector.py
pytermgui/palettes.py
pytermgui/prettifiers.py
pytermgui/pretty.py
pytermgui/py.typed
pytermgui/regex.py
pytermgui/serialization.py
pytermgui/term.py
pytermgui/win32console.py
pytermgui/markup/__init__.py
pytermgui/markup/aliases.py
pytermgui/markup/language.py
pytermgui/markup/macros.py
pytermgui/markup/parsing.py
pytermgui/markup/style_maps.py
pytermgui/markup/tokens.py
pytermgui/widgets/__init__.py
pytermgui/widgets/base.py
pytermgui/widgets/boxes.py
pytermgui/widgets/button.py
pytermgui/widgets/checkbox.py
pytermgui/widgets/collapsible.py
pytermgui/widgets/color_picker.py
pytermgui/widgets/containers.py
pytermgui/widgets/fancy_repr.py
pytermgui/widgets/frames.py
pytermgui/widgets/inline.py
pytermgui/widgets/input_field.py
pytermgui/widgets/keyboard_button.py
pytermgui/widgets/pixel_matrix.py
pytermgui/widgets/slider.py
pytermgui/widgets/styles.py
pytermgui/widgets/toggle.py
pytermgui/window_manager/__init__.py
pytermgui/window_manager/compositor.py
pytermgui/window_manager/layouts.py
pytermgui/window_manager/manager.py
pytermgui/window_manager/window.py
tests/__init__.py
tests/_exporter_targets.py
tests/colorgrids.py
tests/not_test_cell.py
tests/test.json
tests/test.yaml
tests/test_animations.py
tests/test_auto.py
tests/test_colors.py
tests/test_dump_n_load.py
tests/test_exporters.py
tests/test_fancy_repr.py
tests/test_helpers.py
tests/test_highlight_markup_literal.py
tests/test_layouts.py
tests/test_parser.py
tests/test_regex.py
tests/test_styles.py
pytermgui-7.7.1.dist-info/METADATA
pytermgui-7.7.1.dist-info/WHEEL
pytermgui-7.7.1.dist-info/entry_points.txt
pytermgui-7.7.1.dist-info/licenses/LICENSE
pytermgui-7.7.1.dist-info/RECORD
