Metadata-Version: 2.1
Name: PyTermGUI
Version: 7.7.1
Summary: Python TUI framework with mouse support, modular widget system, customizable and rapid terminal markup language and more!
Project-URL: homepage, https://github.com/bczsalba/PyTermGUI
Project-URL: repository, https://github.com/bczsalba/PyTermGUI
Project-URL: documentation, https://ptg.bczsalba.com
Author-email: Balázs Cene <bczsalba@gmail.com>
License: MIT
License-File: LICENSE
Keywords: ANSI,TUI,UI,framework,markup,terminal,user-interface,xterm
Classifier: Development Status :: 5 - Production/Stable
Classifier: Environment :: Console
Classifier: Framework :: IPython
Classifier: Intended Audience :: Developers
Classifier: License :: OSI Approved :: MIT License
Classifier: Operating System :: MacOS
Classifier: Operating System :: POSIX :: Linux
Classifier: Programming Language :: Python :: 3.8
Classifier: Programming Language :: Python :: 3.9
Classifier: Programming Language :: Python :: 3.10
Classifier: Programming Language :: Python :: 3.11
Classifier: Topic :: Software Development :: Libraries
Classifier: Topic :: Terminals
Classifier: Topic :: Text Processing :: Markup
Classifier: Typing :: Typed
Requires-Python: >=3.8
Requires-Dist: typing-extensions
Requires-Dist: wcwidth
Provides-Extra: yaml
Requires-Dist: pyyaml; extra == 'yaml'
